api/__init__.py
api/admin.py
api/apps.py
api/consumers.py
api/forms.py
api/models.py
api/routing.py
api/serializers.py
api/signals.py
api/tests.py
api/urls.py
api/views.py
api/migrations/0001_initial.py
api/migrations/0002_auto_20211209_2257.py
api/migrations/0003_auto_20211209_2328.py
api/migrations/0004_group_groupprofile_messages_profile.py
api/migrations/__init__.py
pass/__init__.py
pass/asgi.py
pass/settings.py
pass/urls.py
pass/wsgi.py
tkm/__init__.py
tkm/admin.py
tkm/apps.py
tkm/forms.py
tkm/models.py
tkm/tests.py
tkm/urls.py
tkm/views.py
tkm/migrations/0001_initial.py
tkm/migrations/0002_auto_20211204_2221.py
tkm/migrations/__init__.py
Pymama-0.1.dist-info/METADATA
Pymama-0.1.dist-info/WHEEL
Pymama-0.1.dist-info/top_level.txt
Pymama-0.1.dist-info/RECORD
