Metadata-Version: 2.1
Name: Pymama
Version: 0.1
Summary: This is Easy
Home-page: UNKNOWN
Author: Pymama
Author-email: tanvirislambaizid64@gmail.com
License: UNKNOWN
Platform: UNKNOWN
Classifier: Programming Language :: Python :: 3
Classifier: License :: OSI Approved :: MIT License
Classifier: Operating System :: OS Independent
